{
  "main": {
    "id": "f512773051844d8f",
    "type": "split",
    "children": [
      {
        "id": "5b5fb5be5183f64a",
        "type": "tabs",
        "children": [
          {
            "id": "364a89f14e96a0a9",
            "type": "leaf",
            "state": {
              "type": "markdown",
              "state": {
                "file": "Базы данных/1. Архитектура баз данных.md",
                "mode": "source",
                "source": false
              }
            }
          },
          {
            "id": "4f3f762f93dc7adb",
            "type": "leaf",
            "state": {
              "type": "markdown",
              "state": {
                "file": "Программирование/1. Базовые средства языка Python.md",
                "mode": "source",
                "source": false
              }
            }
          },
          {
            "id": "7a0551060baa5527",
            "type": "leaf",
            "state": {
              "type": "markdown",
              "state": {
                "file": "Программирование/2. Массивы, структуры, объединения, указатели и их описание.md",
                "mode": "source",
                "source": false
              }
            }
          },
          {
            "id": "3dc6a00e3f61f977",
            "type": "leaf",
            "state": {
              "type": "markdown",
              "state": {
                "file": "Программирование/3. Операторы циклов с предусловием и с постусловием.md",
                "mode": "source",
                "source": false
              }
            }
          },
          {
            "id": "705f2ccef3e3774b",
            "type": "leaf",
            "state": {
              "type": "markdown",
              "state": {
                "file": "Программирование/4. Методы и средства разработки, тестирования и отладки программ на языках высокого уровня.md",
                "mode": "source",
                "source": false
              }
            }
          },
          {
            "id": "471cbf7279e907ad",
            "type": "leaf",
            "state": {
              "type": "markdown",
              "state": {
                "file": "Программирование/5. Структуры данных, данные и алгоритмы.md",
                "mode": "source",
                "source": false
              }
            }
          }
        ],
        "currentTab": 5
      }
    ],
    "direction": "vertical"
  },
  "left": {
    "id": "d005a9341fffe634",
    "type": "split",
    "children": [
      {
        "id": "0c9ae3582e2de316",
        "type": "tabs",
        "children": [
          {
            "id": "4e1f62f6f8f12978",
            "type": "leaf",
            "state": {
              "type": "file-explorer",
              "state": {
                "sortOrder": "alphabetical"
              }
            }
          },
          {
            "id": "2d958af10cc33839",
            "type": "leaf",
            "state": {
              "type": "search",
              "state": {
                "query": "",
                "matchingCase": false,
                "explainSearch": false,
                "collapseAll": false,
                "extraContext": false,
                "sortOrder": "alphabetical"
              }
            }
          },
          {
            "id": "bb3bcef2b701f6f3",
            "type": "leaf",
            "state": {
              "type": "bookmarks",
              "state": {}
            }
          }
        ]
      }
    ],
    "direction": "horizontal",
    "width": 300
  },
  "right": {
    "id": "cf2443cb38bf5880",
    "type": "split",
    "children": [
      {
        "id": "d836f5cd9bfe778a",
        "type": "tabs",
        "children": [
          {
            "id": "c17fc385010049a1",
            "type": "leaf",
            "state": {
              "type": "backlink",
              "state": {
                "file": "Программирование/5. Структуры данных, данные и алгоритмы.md",
                "collapseAll": false,
                "extraContext": false,
                "sortOrder": "alphabetical",
                "showSearch": false,
                "searchQuery": "",
                "backlinkCollapsed": false,
                "unlinkedCollapsed": true
              }
            }
          },
          {
            "id": "ed29c86aa37e8b44",
            "type": "leaf",
            "state": {
              "type": "outgoing-link",
              "state": {
                "file": "Программирование/5. Структуры данных, данные и алгоритмы.md",
                "linksCollapsed": false,
                "unlinkedCollapsed": true
              }
            }
          },
          {
            "id": "019ab72e02f8ea17",
            "type": "leaf",
            "state": {
              "type": "tag",
              "state": {
                "sortOrder": "frequency",
                "useHierarchy": true
              }
            }
          },
          {
            "id": "9751d2aad56a4cfe",
            "type": "leaf",
            "state": {
              "type": "outline",
              "state": {
                "file": "Программирование/5. Структуры данных, данные и алгоритмы.md"
              }
            }
          }
        ]
      }
    ],
    "direction": "horizontal",
    "width": 300,
    "collapsed": true
  },
  "left-ribbon": {
    "hiddenItems": {
      "switcher:Open quick switcher": false,
      "graph:Open graph view": false,
      "canvas:Create new canvas": false,
      "daily-notes:Open today's daily note": false,
      "templates:Insert template": false,
      "command-palette:Open command palette": false
    }
  },
  "active": "4e1f62f6f8f12978",
  "lastOpenFiles": [
    "Базы данных/3. Уровни проектирования базы данных: концептуальный, логический, физический.",
    "Программирование/5. Структуры данных, данные и алгоритмы.md",
    "Программирование/4. Методы и средства разработки, тестирования и отладки программ на языках высокого уровня.md",
    "Программирование/3. Операторы циклов с предусловием и с постусловием.md",
    "Программирование/2. Массивы, структуры, объединения, указатели и их описание.md",
    "Программирование/1. Базовые средства языка Python.md",
    "Программирование",
    "Операционные системы/5. Надежность и безопасность ОС. Сохранность и защита программных систем, защита от сбоев и несанкционированного доступа. Инсайдерские а.md",
    "Операционные системы/4. Управление памятью. Реальная и виртуальная память. Механизм реализации виртуальной памяти. Методы распределения памяти. Совместное и.md",
    "5. Надежность и безопасность ОС. Сохранность и защита программных систем, защита от сбоев и несанкционированного доступа. Инсайдерские атаки. Внешние атаки. Вредоносные программы. Троянские кони, черви и вирусы. Средства защиты от вредоносных программ..md",
    "4. Управление памятью. Реальная и виртуальная память. Механизм реализации виртуальной памяти. Методы распределения памяти. Совместное использование памяти. Защита памяти..md",
    "Операционные системы/3. Файлы и файловые системы. Принципы организации файловых систем. Система управления файлами..md",
    "Операционные системы/2. Понятие вычислительного процесса. Адресное пространство процесса. Идентификатор и дескриптор процесса. Управление вычислительными пр.md",
    "Операционные системы/1. Назначение и основные функции операционных систем. Операционная среда, пользовательский и программный интерфейсы ОС. Виды ресурсов.md",
    "Базы данных/2. Реляционная модель данных.md",
    "2. Понятие вычислительного процесса. Адресное пространство процесса. Идентификатор и дескриптор процесса. Управление вычислительными процессами. Понятие приоритета и очереди процессов..md",
    "Операционные системы/1. Назначение и основные функции операционных систем. Операционная среда, пользовательский и программный интерфейсы ОС. Виды ресурсов..md",
    "Untitled/Назначение и основные функции операционных систем. Операционная среда, пользовательский и программный интерфейсы ОС. Виды ресурсов. Понятие процесса, потока, задачи. Многозадачность. Понятие прерывания..md",
    "Операционные системы",
    "Базы данных/1. Архитектура баз данных.md",
    "Базы данных/Конспект",
    "Базы данных"
  ]
}